roman.py
roman-4.1.dist-info/LICENSE.txt
roman-4.1.dist-info/METADATA
roman-4.1.dist-info/WHEEL
roman-4.1.dist-info/entry_points.txt
roman-4.1.dist-info/top_level.txt
roman-4.1.dist-info/zip-safe
roman-4.1.dist-info/RECORD
