Metadata-Version: 2.1
Name: roman
Version: 4.1
Summary: Integer to Roman numerals converter
Home-page: https://github.com/zopefoundation/roman
Author: Mark Pilgrim
Maintainer: Zope Foundation and Contributors
Maintainer-email: zope-dev@zope.dev
License: ZPL 2.1
Keywords: roman
Platform: UNKNOWN
Classifier: Development Status :: 5 - Production/Stable
Classifier: Intended Audience :: Developers
Classifier: Programming Language :: Python
Classifier: Programming Language :: Python :: 3
Classifier: Programming Language :: Python :: 3.7
Classifier: Programming Language :: Python :: 3.8
Classifier: Programming Language :: Python :: 3.9
Classifier: Programming Language :: Python :: 3.10
Classifier: Programming Language :: Python :: 3.11
Classifier: Programming Language :: Python :: Implementation :: CPython
Classifier: Programming Language :: Python :: Implementation :: PyPy
Classifier: License :: OSI Approved :: Zope Public License
Classifier: Programming Language :: Python
Classifier: Natural Language :: English
Classifier: Operating System :: OS Independent
Requires-Python: >=3.7
